MANIFEST.in
README.md
setup.py
sockjsroom/__init__.py
sockjsroom/httpJsonHandler.py
sockjsroom/jsonParser.py
sockjsroom/socketHandler.py
sockjsroom/structure.py
sockjsroom.egg-info/PKG-INFO
sockjsroom.egg-info/SOURCES.txt
sockjsroom.egg-info/dependency_links.txt
sockjsroom.egg-info/requires.txt
sockjsroom.egg-info/top_level.txt