Metadata-Version: 1.0
Name: sockjsroom
Version: 0.0.3
Summary: Sockjs-tornado multi room system
Home-page: https://github.com/Deisss/python-sockjsroom
Author: Deisss
Author-email: deisss@free.fr
License: UNKNOWN
Platform: UNKNOWN
Classifier: Programming Language :: Python
Classifier: Development Status :: 1 - Planning
Classifier: License :: OSI Approved :: MIT License
Classifier: Natural Language :: English
Classifier: Operating System :: OS Independent
Classifier: Programming Language :: Python :: 2.6
Classifier: Topic :: Communications
